sampleclient/__init__.py
sampleclient/client.py
sampleclient/const.py
sampleclient-0.1.0.dist-info/LICENSE
sampleclient-0.1.0.dist-info/METADATA
sampleclient-0.1.0.dist-info/WHEEL
sampleclient-0.1.0.dist-info/top_level.txt
sampleclient-0.1.0.dist-info/RECORD
