Metadata-Version: 2.1
Name: sampleclient
Version: 0.1.0
Summary: Sample Client lib.
Home-page: https://github.com/ludeeus/sampleclient
Author: Joakim Sorensen
Author-email: hi@ludeeus.com
License: UNKNOWN
Platform: UNKNOWN
Classifier: Programming Language :: Python :: 3
Classifier: License :: OSI Approved :: MIT License
Classifier: Operating System :: OS Independent
